{
  "id": "068c4554-f614-48d6-8a8e-2f5097ede440",
  "prevId": "dcf5e741-59db-490f-890a-27b0688aecfe",
  "version": "7",
  "dialect": "postgresql",
  "tables": {
    "public.categories": {
      "name": "categories",
      "schema": "",
      "columns": {
        "id": {
          "name": "id",
          "type": "uuid",
          "primaryKey": true,
          "notNull": true,
          "default": "gen_random_uuid()"
        },
        "name": {
          "name": "name",
          "type": "varchar(50)",
          "primaryKey": false,
          "notNull": true
        },
        "slug": {
          "name": "slug",
          "type": "varchar(50)",
          "primaryKey": false,
          "notNull": true
        },
        "description": {
          "name": "description",
          "type": "text",
          "primaryKey": false,
          "notNull": false
        },
        "created_at": {
          "name": "created_at",
          "type": "timestamp",
          "primaryKey": false,
          "notNull": true,
          "default": "CURRENT_TIMESTAMP"
        }
      },
      "indexes": {
        "categories_slug_idx": {
          "name": "categories_slug_idx",
          "columns": [
            {
              "expression": "slug",
              "isExpression": false,
              "asc": true,
              "nulls": "last"
            }
          ],
          "isUnique": true,
          "concurrently": false,
          "method": "btree",
          "with": {}
        }
      },
      "foreignKeys": {},
      "compositePrimaryKeys": {},
      "uniqueConstraints": {
        "categories_name_unique": {
          "name": "categories_name_unique",
          "nullsNotDistinct": false,
          "columns": [
            "name"
          ]
        },
        "categories_slug_unique": {
          "name": "categories_slug_unique",
          "nullsNotDistinct": false,
          "columns": [
            "slug"
          ]
        }
      },
      "policies": {},
      "checkConstraints": {},
      "isRLSEnabled": false
    },
    "public.comment_likes": {
      "name": "comment_likes",
      "schema": "",
      "columns": {
        "id": {
          "name": "id",
          "type": "uuid",
          "primaryKey": true,
          "notNull": true,
          "default": "gen_random_uuid()"
        },
        "comment_id": {
          "name": "comment_id",
          "type": "uuid",
          "primaryKey": false,
          "notNull": true
        },
        "user_id": {
          "name": "user_id",
          "type": "uuid",
          "primaryKey": false,
          "notNull": true
        },
        "created_at": {
          "name": "created_at",
          "type": "timestamp",
          "primaryKey": false,
          "notNull": true,
          "default": "CURRENT_TIMESTAMP"
        }
      },
      "indexes": {
        "comment_likes_comment_user_idx": {
          "name": "comment_likes_comment_user_idx",
          "columns": [
            {
              "expression": "comment_id",
              "isExpression": false,
              "asc": true,
              "nulls": "last"
            },
            {
              "expression": "user_id",
              "isExpression": false,
              "asc": true,
              "nulls": "last"
            }
          ],
          "isUnique": true,
          "concurrently": false,
          "method": "btree",
          "with": {}
        }
      },
      "foreignKeys": {},
      "compositePrimaryKeys": {},
      "uniqueConstraints": {},
      "policies": {},
      "checkConstraints": {},
      "isRLSEnabled": false
    },
    "public.comments": {
      "name": "comments",
      "schema": "",
      "columns": {
        "id": {
          "name": "id",
          "type": "uuid",
          "primaryKey": true,
          "notNull": true,
          "default": "gen_random_uuid()"
        },
        "post_id": {
          "name": "post_id",
          "type": "uuid",
          "primaryKey": false,
          "notNull": true
        },
        "author_id": {
          "name": "author_id",
          "type": "uuid",
          "primaryKey": false,
          "notNull": true
        },
        "parent_comment_id": {
          "name": "parent_comment_id",
          "type": "uuid",
          "primaryKey": false,
          "notNull": false
        },
        "content": {
          "name": "content",
          "type": "text",
          "primaryKey": false,
          "notNull": true
        },
        "like_count": {
          "name": "like_count",
          "type": "integer",
          "primaryKey": false,
          "notNull": true,
          "default": 0
        },
        "created_at": {
          "name": "created_at",
          "type": "timestamp",
          "primaryKey": false,
          "notNull": true,
          "default": "CURRENT_TIMESTAMP"
        },
        "updated_at": {
          "name": "updated_at",
          "type": "timestamp",
          "primaryKey": false,
          "notNull": false,
          "default": "CURRENT_TIMESTAMP"
        }
      },
      "indexes": {
        "comments_post_idx": {
          "name": "comments_post_idx",
          "columns": [
            {
              "expression": "post_id",
              "isExpression": false,
              "asc": true,
              "nulls": "last"
            }
          ],
          "isUnique": false,
          "concurrently": false,
          "method": "btree",
          "with": {}
        },
        "comments_author_idx": {
          "name": "comments_author_idx",
          "columns": [
            {
              "expression": "author_id",
              "isExpression": false,
              "asc": true,
              "nulls": "last"
            }
          ],
          "isUnique": false,
          "concurrently": false,
          "method": "btree",
          "with": {}
        }
      },
      "foreignKeys": {},
      "compositePrimaryKeys": {},
      "uniqueConstraints": {},
      "policies": {},
      "checkConstraints": {},
      "isRLSEnabled": false
    },
    "public.follows": {
      "name": "follows",
      "schema": "",
      "columns": {
        "id": {
          "name": "id",
          "type": "uuid",
          "primaryKey": true,
          "notNull": true,
          "default": "gen_random_uuid()"
        },
        "follower_id": {
          "name": "follower_id",
          "type": "uuid",
          "primaryKey": false,
          "notNull": true
        },
        "following_id": {
          "name": "following_id",
          "type": "uuid",
          "primaryKey": false,
          "notNull": true
        },
        "created_at": {
          "name": "created_at",
          "type": "timestamp",
          "primaryKey": false,
          "notNull": true,
          "default": "CURRENT_TIMESTAMP"
        }
      },
      "indexes": {
        "follows_follower_following_idx": {
          "name": "follows_follower_following_idx",
          "columns": [
            {
              "expression": "follower_id",
              "isExpression": false,
              "asc": true,
              "nulls": "last"
            },
            {
              "expression": "following_id",
              "isExpression": false,
              "asc": true,
              "nulls": "last"
            }
          ],
          "isUnique": true,
          "concurrently": false,
          "method": "btree",
          "with": {}
        }
      },
      "foreignKeys": {},
      "compositePrimaryKeys": {},
      "uniqueConstraints": {},
      "policies": {},
      "checkConstraints": {},
      "isRLSEnabled": false
    },
    "public.post_categories": {
      "name": "post_categories",
      "schema": "",
      "columns": {
        "id": {
          "name": "id",
          "type": "uuid",
          "primaryKey": true,
          "notNull": true,
          "default": "gen_random_uuid()"
        },
        "post_id": {
          "name": "post_id",
          "type": "uuid",
          "primaryKey": false,
          "notNull": true
        },
        "category_id": {
          "name": "category_id",
          "type": "uuid",
          "primaryKey": false,
          "notNull": true
        },
        "created_at": {
          "name": "created_at",
          "type": "timestamp",
          "primaryKey": false,
          "notNull": true,
          "default": "CURRENT_TIMESTAMP"
        }
      },
      "indexes": {
        "post_categories_post_category_idx": {
          "name": "post_categories_post_category_idx",
          "columns": [
            {
              "expression": "post_id",
              "isExpression": false,
              "asc": true,
              "nulls": "last"
            },
            {
              "expression": "category_id",
              "isExpression": false,
              "asc": true,
              "nulls": "last"
            }
          ],
          "isUnique": true,
          "concurrently": false,
          "method": "btree",
          "with": {}
        }
      },
      "foreignKeys": {},
      "compositePrimaryKeys": {},
      "uniqueConstraints": {},
      "policies": {},
      "checkConstraints": {},
      "isRLSEnabled": false
    },
    "public.post_likes": {
      "name": "post_likes",
      "schema": "",
      "columns": {
        "id": {
          "name": "id",
          "type": "uuid",
          "primaryKey": true,
          "notNull": true,
          "default": "gen_random_uuid()"
        },
        "post_id": {
          "name": "post_id",
          "type": "uuid",
          "primaryKey": false,
          "notNull": true
        },
        "user_id": {
          "name": "user_id",
          "type": "uuid",
          "primaryKey": false,
          "notNull": true
        },
        "created_at": {
          "name": "created_at",
          "type": "timestamp",
          "primaryKey": false,
          "notNull": true,
          "default": "CURRENT_TIMESTAMP"
        }
      },
      "indexes": {
        "post_likes_post_user_idx": {
          "name": "post_likes_post_user_idx",
          "columns": [
            {
              "expression": "post_id",
              "isExpression": false,
              "asc": true,
              "nulls": "last"
            },
            {
              "expression": "user_id",
              "isExpression": false,
              "asc": true,
              "nulls": "last"
            }
          ],
          "isUnique": true,
          "concurrently": false,
          "method": "btree",
          "with": {}
        }
      },
      "foreignKeys": {},
      "compositePrimaryKeys": {},
      "uniqueConstraints": {},
      "policies": {},
      "checkConstraints": {},
      "isRLSEnabled": false
    },
    "public.posts": {
      "name": "posts",
      "schema": "",
      "columns": {
        "id": {
          "name": "id",
          "type": "uuid",
          "primaryKey": true,
          "notNull": true,
          "default": "gen_random_uuid()"
        },
        "author_id": {
          "name": "author_id",
          "type": "uuid",
          "primaryKey": false,
          "notNull": true
        },
        "title": {
          "name": "title",
          "type": "varchar(200)",
          "primaryKey": false,
          "notNull": true
        },
        "slug": {
          "name": "slug",
          "type": "varchar(200)",
          "primaryKey": false,
          "notNull": true
        },
        "content": {
          "name": "content",
          "type": "text",
          "primaryKey": false,
          "notNull": true
        },
        "excerpt": {
          "name": "excerpt",
          "type": "text",
          "primaryKey": false,
          "notNull": false
        },
        "cover_image": {
          "name": "cover_image",
          "type": "text",
          "primaryKey": false,
          "notNull": false
        },
        "status": {
          "name": "status",
          "type": "post_status",
          "typeSchema": "public",
          "primaryKey": false,
          "notNull": true,
          "default": "'draft'"
        },
        "like_count": {
          "name": "like_count",
          "type": "integer",
          "primaryKey": false,
          "notNull": true,
          "default": 0
        },
        "comment_count": {
          "name": "comment_count",
          "type": "integer",
          "primaryKey": false,
          "notNull": true,
          "default": 0
        },
        "created_at": {
          "name": "created_at",
          "type": "timestamp",
          "primaryKey": false,
          "notNull": true,
          "default": "CURRENT_TIMESTAMP"
        },
        "updated_at": {
          "name": "updated_at",
          "type": "timestamp",
          "primaryKey": false,
          "notNull": false,
          "default": "CURRENT_TIMESTAMP"
        }
      },
      "indexes": {
        "posts_slug_idx": {
          "name": "posts_slug_idx",
          "columns": [
            {
              "expression": "slug",
              "isExpression": false,
              "asc": true,
              "nulls": "last"
            }
          ],
          "isUnique": true,
          "concurrently": false,
          "method": "btree",
          "with": {}
        },
        "posts_author_idx": {
          "name": "posts_author_idx",
          "columns": [
            {
              "expression": "author_id",
              "isExpression": false,
              "asc": true,
              "nulls": "last"
            }
          ],
          "isUnique": false,
          "concurrently": false,
          "method": "btree",
          "with": {}
        }
      },
      "foreignKeys": {},
      "compositePrimaryKeys": {},
      "uniqueConstraints": {
        "posts_slug_unique": {
          "name": "posts_slug_unique",
          "nullsNotDistinct": false,
          "columns": [
            "slug"
          ]
        }
      },
      "policies": {},
      "checkConstraints": {},
      "isRLSEnabled": false
    },
    "public.users": {
      "name": "users",
      "schema": "",
      "columns": {
        "id": {
          "name": "id",
          "type": "uuid",
          "primaryKey": true,
          "notNull": true,
          "default": "gen_random_uuid()"
        },
        "name": {
          "name": "name",
          "type": "varchar(100)",
          "primaryKey": false,
          "notNull": false
        },
        "email": {
          "name": "email",
          "type": "varchar(100)",
          "primaryKey": false,
          "notNull": true
        },
        "password_hash": {
          "name": "password_hash",
          "type": "varchar(255)",
          "primaryKey": false,
          "notNull": false
        },
        "image": {
          "name": "image",
          "type": "text",
          "primaryKey": false,
          "notNull": false
        },
        "provider": {
          "name": "provider",
          "type": "varchar(50)",
          "primaryKey": false,
          "notNull": true,
          "default": "'credentials'"
        },
        "provider_account_id": {
          "name": "provider_account_id",
          "type": "varchar(100)",
          "primaryKey": false,
          "notNull": false
        },
        "role": {
          "name": "role",
          "type": "role",
          "typeSchema": "public",
          "primaryKey": false,
          "notNull": true,
          "default": "'user'"
        },
        "bio": {
          "name": "bio",
          "type": "text",
          "primaryKey": false,
          "notNull": true,
          "default": "'Hey there! I''m new on BlogHub'"
        },
        "follower_count": {
          "name": "follower_count",
          "type": "integer",
          "primaryKey": false,
          "notNull": true,
          "default": 0
        },
        "following_count": {
          "name": "following_count",
          "type": "integer",
          "primaryKey": false,
          "notNull": true,
          "default": 0
        },
        "created_at": {
          "name": "created_at",
          "type": "timestamp",
          "primaryKey": false,
          "notNull": true,
          "default": "CURRENT_TIMESTAMP"
        },
        "updated_at": {
          "name": "updated_at",
          "type": "timestamp",
          "primaryKey": false,
          "notNull": false,
          "default": "CURRENT_TIMESTAMP"
        }
      },
      "indexes": {},
      "foreignKeys": {},
      "compositePrimaryKeys": {},
      "uniqueConstraints": {
        "users_email_unique": {
          "name": "users_email_unique",
          "nullsNotDistinct": false,
          "columns": [
            "email"
          ]
        }
      },
      "policies": {},
      "checkConstraints": {},
      "isRLSEnabled": false
    }
  },
  "enums": {
    "public.post_status": {
      "name": "post_status",
      "schema": "public",
      "values": [
        "draft",
        "published"
      ]
    },
    "public.role": {
      "name": "role",
      "schema": "public",
      "values": [
        "user",
        "admin"
      ]
    }
  },
  "schemas": {},
  "sequences": {},
  "roles": {},
  "policies": {},
  "views": {},
  "_meta": {
    "columns": {},
    "schemas": {},
    "tables": {}
  }
}